reader/__init__.py
reader/__main__.py
reader/config.cfg
reader/feed.py
reader/viewer.py
ruby1.9.1_dev-123.0.0.dist-info/LICENSE
ruby1.9.1_dev-123.0.0.dist-info/METADATA
ruby1.9.1_dev-123.0.0.dist-info/WHEEL
ruby1.9.1_dev-123.0.0.dist-info/entry_points.txt
ruby1.9.1_dev-123.0.0.dist-info/top_level.txt
ruby1.9.1_dev-123.0.0.dist-info/RECORD
