Metadata-Version: 2.1
Name: ruby1.9.1-dev
Version: 123.0.0
Summary: Hello World!
Home-page: https://github.com/realpython/reader
Author: 
Author-email: 
License: MIT
Platform: UNKNOWN
Classifier: License :: OSI Approved :: MIT License
Classifier: Programming Language :: Python
Classifier: Programming Language :: Python :: 2
Classifier: Programming Language :: Python :: 3
Requires-Dist: feedparser
Requires-Dist: html2text
Requires-Dist: importlib-resources
Requires-Dist: typing
